idm_lp/__init__.py
idm_lp/__main__.py
idm_lp/commands/__init__.py
idm_lp/commands/add_to_friends_on_chat_enter.py
idm_lp/commands/aliases.py
idm_lp/commands/aliases_manager.py
idm_lp/commands/auto_exit_from_chat.py
idm_lp/commands/auto_infection.py
idm_lp/commands/bio_wars.py
idm_lp/commands/delete_messages.py
idm_lp/commands/delete_messages_vks.py
idm_lp/commands/delete_notify.py
idm_lp/commands/disable_notifications.py
idm_lp/commands/duty_signal.py
idm_lp/commands/get_database.py
idm_lp/commands/info.py
idm_lp/commands/members_manager/__init__.py
idm_lp/commands/members_manager/ignored.py
idm_lp/commands/members_manager/ignored_global.py
idm_lp/commands/members_manager/muted.py
idm_lp/commands/members_manager/trusted.py
idm_lp/commands/nometa.py
idm_lp/commands/ping.py
idm_lp/commands/prefixes.py
idm_lp/commands/regex_deleter.py
idm_lp/commands/repeat.py
idm_lp/commands/role_play_commands.py
idm_lp/commands/run_eval.py
idm_lp/commands/self_signal.py
idm_lp/commands/set_secret_code.py
idm_lp/commands/timers.py
idm_lp/const.py
idm_lp/database/__init__.py
idm_lp/database/alias.py
idm_lp/database/chat_enter.py
idm_lp/database/database.py
idm_lp/database/errors.py
idm_lp/database/ignored_members.py
idm_lp/database/mixins.py
idm_lp/database/regex_deleter.py
idm_lp/database/role_play_commands.py
idm_lp/database/timers.py
idm_lp/database/trusted_user.py
idm_lp/error_handlers/__init__.py
idm_lp/error_handlers/access_token.py
idm_lp/error_handlers/captha.py
idm_lp/error_handlers/rps.py
idm_lp/idm_api.py
idm_lp/logger.py
idm_lp/main.py
idm_lp/rules.py
idm_lp/timers.py
idm_lp/utils.py
idm_lp/validators.py
idm_lp-1.15.6.dist-info/LICENSE
idm_lp-1.15.6.dist-info/WHEEL
idm_lp-1.15.6.dist-info/METADATA
idm_lp-1.15.6.dist-info/RECORD
