Metadata-Version: 2.1
Name: idm-lp
Version: 1.15.6
Summary: LP модуль позволяет работать приемнику сигналов «IDM» работать в любых чатах.
Home-page: https://idmduty.ru
License: MIT
Author: lordralinc
Requires-Python: >=3.8,<4.0
Classifier: License :: OSI Approved :: MIT License
Classifier: Programming Language :: Python :: 3
Classifier: Programming Language :: Python :: 3.10
Classifier: Programming Language :: Python :: 3.8
Classifier: Programming Language :: Python :: 3.9
Requires-Dist: APScheduler (>=3.9.1,<4.0)
Requires-Dist: pydantic (>=1.7.3,<2.0)
Requires-Dist: python-rucaptcha (>=3.0,<4.0)
Requires-Dist: vkbottle (>=2.7.12,<3.0.0)
Project-URL: Documentation, https://github.com/IDM-Team/idm_lp
Project-URL: Repository, https://github.com/IDM-Team/idm_lp
